[
  {
    "id": "h-reyes-0",
    "officerId": "h-reyes",
    "market": "Houston",
    "customer": "Northstar Tech",
    "product": "Deposits",
    "stage": "Qualified",
    "amount": 1986780.752749635,
    "probability": 0.2966344724409282,
    "daysInStage": 45,
    "ageDays": 84,
    "expectedClose": "2026-11-05",
    "revAnnual": 9933.903763748174
  },
  {
    "id": "h-reyes-1",
    "officerId": "h-reyes",
    "market": "Houston",
    "customer": "Oakridge Auto",
    "product": "TM",
    "stage": "Closed",
    "amount": 56255.37604326382,
    "probability": 1,
    "daysInStage": 58,
    "ageDays": 203,
    "expectedClose": "2026-07-07",
    "revAnnual": 56255.37604326382
  },
  {
    "id": "h-reyes-2",
    "officerId": "h-reyes",
    "market": "Houston",
    "customer": "Pacific Imports",
    "product": "TM",
    "stage": "Proposal",
    "amount": 204686.79094687104,
    "probability": 0.5004163671517745,
    "daysInStage": 65,
    "ageDays": 155,
    "expectedClose": "2026-09-15",
    "revAnnual": 204686.79094687104
  },
  {
    "id": "h-reyes-3",
    "officerId": "h-reyes",
    "market": "Houston",
    "customer": "Quartz Mining",
    "product": "Deposits",
    "stage": "Closed",
    "amount": 779213.0107978485,
    "probability": 0.9740337510826066,
    "daysInStage": 16,
    "ageDays": 160,
    "expectedClose": "2026-07-28",
    "revAnnual": 3896.065053989242
  },
  {
    "id": "h-reyes-4",
    "officerId": "h-reyes",
    "market": "Houston",
    "customer": "Redwood Construction",
    "product": "Deposits",
    "stage": "Qualified",
    "amount": 2490783.843762691,
    "probability": 0.23336697861086578,
    "daysInStage": 75,
    "ageDays": 121,
    "expectedClose": "2026-11-25",
    "revAnnual": 12453.919218813457
  },
  {
    "id": "h-reyes-5",
    "officerId": "h-reyes",
    "market": "Houston",
    "customer": "Summit Hospitality",
    "product": "Other",
    "stage": "Qualified",
    "amount": 56309.16841654107,
    "probability": 0.2151652165222913,
    "daysInStage": 53,
    "ageDays": 97,
    "expectedClose": "2026-10-16",
    "revAnnual": 56309.16841654107
  },
  {
    "id": "h-reyes-6",
    "officerId": "h-reyes",
    "market": "Houston",
    "customer": "Trinity Pharma",
    "product": "Other",
    "stage": "Lead",
    "amount": 36726.20540484786,
    "probability": 0.06573388492688537,
    "daysInStage": 51,
    "ageDays": 79,
    "expectedClose": "2026-11-04",
    "revAnnual": 36726.20540484786
  },
  {
    "id": "h-reyes-7",
    "officerId": "h-reyes",
    "market": "Houston",
    "customer": "Union Distributors",
    "product": "CommLoan",
    "stage": "Qualified",
    "amount": 1681430.4142695335,
    "probability": 0.22000934309326112,
    "daysInStage": 88,
    "ageDays": 145,
    "expectedClose": "2026-11-06",
    "revAnnual": 57168.63408516414
  },
  {
    "id": "h-reyes-8",
    "officerId": "h-reyes",
    "market": "Houston",
    "customer": "Vanguard Plastics",
    "product": "Deposits",
    "stage": "Commit",
    "amount": 1591906.9281137304,
    "probability": 0.7976867821300403,
    "daysInStage": 47,
    "ageDays": 165,
    "expectedClose": "2026-08-29",
    "revAnnual": 7959.534640568652
  },
  {
    "id": "h-reyes-9",
    "officerId": "h-reyes",
    "market": "Houston",
    "customer": "Westfield Retail",
    "product": "Deposits",
    "stage": "Lead",
    "amount": 5644082.342413204,
    "probability": 0.090537016117014,
    "daysInStage": 38,
    "ageDays": 55,
    "expectedClose": "2026-12-24",
    "revAnnual": 28220.41171206602
  },
  {
    "id": "h-reyes-10",
    "officerId": "h-reyes",
    "market": "Houston",
    "customer": "Yellowstone Ranch",
    "product": "CommLoan",
    "stage": "Lead",
    "amount": 2214860.592567027,
    "probability": 0.12286659302189946,
    "daysInStage": 45,
    "ageDays": 67,
    "expectedClose": "2026-12-02",
    "revAnnual": 75305.26014727892
  },
  {
    "id": "h-reyes-11",
    "officerId": "h-reyes",
    "market": "Houston",
    "customer": "Zenith Software",
    "product": "Deposits",
    "stage": "Lead",
    "amount": 631615.2739707652,
    "probability": 0.14116969865281137,
    "daysInStage": 24,
    "ageDays": 31,
    "expectedClose": "2026-12-08",
    "revAnnual": 3158.076369853826
  },
  {
    "id": "h-reyes-12",
    "officerId": "h-reyes",
    "market": "Houston",
    "customer": "Alamo Equipment",
    "product": "CommLoan",
    "stage": "Closed",
    "amount": 815121.374427569,
    "probability": 1,
    "daysInStage": 37,
    "ageDays": 185,
    "expectedClose": "2026-08-08",
    "revAnnual": 27714.126730537348
  },
  {
    "id": "h-reyes-13",
    "officerId": "h-reyes",
    "market": "Houston",
    "customer": "Brazos Petroleum",
    "product": "TM",
    "stage": "Proposal",
    "amount": 258735.1896497421,
    "probability": 0.48768674666061995,
    "daysInStage": 17,
    "ageDays": 98,
    "expectedClose": "2026-08-30",
    "revAnnual": 258735.1896497421
  },
  {
    "id": "h-patel-0",
    "officerId": "h-patel",
    "market": "Houston",
    "customer": "Zenith Software",
    "product": "Deposits",
    "stage": "Lead",
    "amount": 3805889.470379005,
    "probability": 0.1462380021577701,
    "daysInStage": 88,
    "ageDays": 89,
    "expectedClose": "2026-12-27",
    "revAnnual": 19029.447351895025
  },
  {
    "id": "h-patel-1",
    "officerId": "h-patel",
    "market": "Houston",
    "customer": "Alamo Equipment",
    "product": "Other",
    "stage": "Lead",
    "amount": 44796.73284711316,
    "probability": 0.09779870598576963,
    "daysInStage": 90,
    "ageDays": 120,
    "expectedClose": "2026-11-10",
    "revAnnual": 44796.73284711316
  },
  {
    "id": "h-patel-2",
    "officerId": "h-patel",
    "market": "Houston",
    "customer": "Brazos Petroleum",
    "product": "Other",
    "stage": "Commit",
    "amount": 21234.434655867517,
    "probability": 0.7959317384753377,
    "daysInStage": 15,
    "ageDays": 106,
    "expectedClose": "2026-08-10",
    "revAnnual": 21234.434655867517
  },
  {
    "id": "h-patel-3",
    "officerId": "h-patel",
    "market": "Houston",
    "customer": "Cedar Cabinetry",
    "product": "Deposits",
    "stage": "Qualified",
    "amount": 664568.04218806,
    "probability": 0.2805072119925171,
    "daysInStage": 19,
    "ageDays": 67,
    "expectedClose": "2026-11-13",
    "revAnnual": 3322.8402109403
  },
  {
    "id": "h-patel-4",
    "officerId": "h-patel",
    "market": "Houston",
    "customer": "Driftwood Hotels",
    "product": "Other",
    "stage": "Proposal",
    "amount": 51592.104418668896,
    "probability": 0.5393878709990532,
    "daysInStage": 28,
    "ageDays": 97,
    "expectedClose": "2026-10-15",
    "revAnnual": 51592.104418668896
  },
  {
    "id": "h-patel-5",
    "officerId": "h-patel",
    "market": "Houston",
    "customer": "Acme Holdings",
    "product": "Deposits",
    "stage": "Commit",
    "amount": 5523470.114967437,
    "probability": 0.7583342947997154,
    "daysInStage": 73,
    "ageDays": 174,
    "expectedClose": "2026-08-19",
    "revAnnual": 27617.350574837186
  },
  {
    "id": "h-patel-6",
    "officerId": "h-patel",
    "market": "Houston",
    "customer": "Beacon Industries",
    "product": "TM",
    "stage": "Proposal",
    "amount": 154984.0535246767,
    "probability": 0.5371772957500071,
    "daysInStage": 80,
    "ageDays": 166,
    "expectedClose": "2026-09-21",
    "revAnnual": 154984.0535246767
  },
  {
    "id": "h-patel-7",
    "officerId": "h-patel",
    "market": "Houston",
    "customer": "Cypress Group",
    "product": "CommLoan",
    "stage": "Lead",
    "amount": 1294674.4504428124,
    "probability": 0.13224937755148858,
    "daysInStage": 63,
    "ageDays": 85,
    "expectedClose": "2026-12-08",
    "revAnnual": 44018.931315055626
  },
  {
    "id": "h-patel-8",
    "officerId": "h-patel",
    "market": "Houston",
    "customer": "Delta Manufacturing",
    "product": "CommLoan",
    "stage": "Closed",
    "amount": 670519.5689699659,
    "probability": 1,
    "daysInStage": 11,
    "ageDays": 148,
    "expectedClose": "2026-07-13",
    "revAnnual": 22797.665344978843
  },
  {
    "id": "h-patel-9",
    "officerId": "h-patel",
    "market": "Houston",
    "customer": "Evergreen Realty",
    "product": "CommLoan",
    "stage": "Commit",
    "amount": 7093495.942013834,
    "probability": 0.8164970132056624,
    "daysInStage": 53,
    "ageDays": 149,
    "expectedClose": "2026-08-28",
    "revAnnual": 241178.86202847035
  },
  {
    "id": "h-patel-10",
    "officerId": "h-patel",
    "market": "Houston",
    "customer": "Galleon Logistics",
    "product": "CommLoan",
    "stage": "Qualified",
    "amount": 3025189.4419490984,
    "probability": 0.25896584349684415,
    "daysInStage": 29,
    "ageDays": 87,
    "expectedClose": "2026-11-02",
    "revAnnual": 102856.44102626936
  },
  {
    "id": "h-patel-11",
    "officerId": "h-patel",
    "market": "Houston",
    "customer": "Harbor Partners",
    "product": "TM",
    "stage": "Qualified",
    "amount": 118290.88356113061,
    "probability": 0.28552366988733413,
    "daysInStage": 33,
    "ageDays": 91,
    "expectedClose": "2026-09-30",
    "revAnnual": 118290.88356113061
  },
  {
    "id": "h-patel-12",
    "officerId": "h-patel",
    "market": "Houston",
    "customer": "Ironwood Capital",
    "product": "CommLoan",
    "stage": "Lead",
    "amount": 652838.681675053,
    "probability": 0.08629365651868284,
    "daysInStage": 28,
    "ageDays": 50,
    "expectedClose": "2026-12-12",
    "revAnnual": 22196.5151769518
  },
  {
    "id": "h-patel-13",
    "officerId": "h-patel",
    "market": "Houston",
    "customer": "Juniper Foods",
    "product": "CommLoan",
    "stage": "Closed",
    "amount": 1212020.7241254319,
    "probability": 1,
    "daysInStage": 34,
    "ageDays": 154,
    "expectedClose": "2026-07-26",
    "revAnnual": 41208.70462026469
  },
  {
    "id": "h-tran-0",
    "officerId": "h-tran",
    "market": "Houston",
    "customer": "Cedar Cabinetry",
    "product": "CommLoan",
    "stage": "Lead",
    "amount": 1005286.409578336,
    "probability": 0.05807494998443872,
    "daysInStage": 74,
    "ageDays": 81,
    "expectedClose": "2026-11-11",
    "revAnnual": 34179.73792566343
  },
  {
    "id": "h-tran-1",
    "officerId": "h-tran",
    "market": "Houston",
    "customer": "Driftwood Hotels",
    "product": "TM",
    "stage": "Commit",
    "amount": 76930.68996537477,
    "probability": 0.7639628823613749,
    "daysInStage": 83,
    "ageDays": 202,
    "expectedClose": "2026-09-04",
    "revAnnual": 76930.68996537477
  },
  {
    "id": "h-tran-2",
    "officerId": "h-tran",
    "market": "Houston",
    "customer": "Acme Holdings",
    "product": "CommLoan",
    "stage": "Qualified",
    "amount": 8942929.718676345,
    "probability": 0.2500789763405919,
    "daysInStage": 40,
    "ageDays": 78,
    "expectedClose": "2026-10-31",
    "revAnnual": 304059.6104349958
  },
  {
    "id": "h-tran-3",
    "officerId": "h-tran",
    "market": "Houston",
    "customer": "Beacon Industries",
    "product": "Deposits",
    "stage": "Lead",
    "amount": 2437446.784970643,
    "probability": 0.14493016125634314,
    "daysInStage": 11,
    "ageDays": 31,
    "expectedClose": "2026-11-04",
    "revAnnual": 12187.233924853215
  },
  {
    "id": "h-tran-4",
    "officerId": "h-tran",
    "market": "Houston",
    "customer": "Cypress Group",
    "product": "CommLoan",
    "stage": "Proposal",
    "amount": 6584533.200003929,
    "probability": 0.495425940817222,
    "daysInStage": 69,
    "ageDays": 137,
    "expectedClose": "2026-10-03",
    "revAnnual": 223874.12880013362
  },
  {
    "id": "h-tran-5",
    "officerId": "h-tran",
    "market": "Houston",
    "customer": "Delta Manufacturing",
    "product": "Other",
    "stage": "Qualified",
    "amount": 26664.60966737941,
    "probability": 0.26675245745573195,
    "daysInStage": 20,
    "ageDays": 78,
    "expectedClose": "2026-11-24",
    "revAnnual": 26664.60966737941
  },
  {
    "id": "h-tran-6",
    "officerId": "h-tran",
    "market": "Houston",
    "customer": "Evergreen Realty",
    "product": "Other",
    "stage": "Proposal",
    "amount": 67793.99687889963,
    "probability": 0.5078452450688928,
    "daysInStage": 10,
    "ageDays": 94,
    "expectedClose": "2026-09-09",
    "revAnnual": 67793.99687889963
  },
  {
    "id": "h-tran-7",
    "officerId": "h-tran",
    "market": "Houston",
    "customer": "Fairfield Energy",
    "product": "Deposits",
    "stage": "Closed",
    "amount": 713863.4488536143,
    "probability": 1,
    "daysInStage": 39,
    "ageDays": 168,
    "expectedClose": "2026-07-25",
    "revAnnual": 3569.3172442680716
  },
  {
    "id": "h-tran-8",
    "officerId": "h-tran",
    "market": "Houston",
    "customer": "Galleon Logistics",
    "product": "CommLoan",
    "stage": "Proposal",
    "amount": 4952275.328447817,
    "probability": 0.530060442793183,
    "daysInStage": 12,
    "ageDays": 100,
    "expectedClose": "2026-10-18",
    "revAnnual": 168377.36116722578
  },
  {
    "id": "h-tran-9",
    "officerId": "h-tran",
    "market": "Houston",
    "customer": "Harbor Partners",
    "product": "CommLoan",
    "stage": "Lead",
    "amount": 16637851.992595503,
    "probability": 0.11826178955379874,
    "daysInStage": 58,
    "ageDays": 87,
    "expectedClose": "2026-12-14",
    "revAnnual": 565686.9677482472
  },
  {
    "id": "h-tran-10",
    "officerId": "h-tran",
    "market": "Houston",
    "customer": "Harbor Partners",
    "product": "Deposits",
    "stage": "Lead",
    "amount": 2865543.015427641,
    "probability": 0.13555655761156232,
    "daysInStage": 65,
    "ageDays": 93,
    "expectedClose": "2026-10-31",
    "revAnnual": 14327.715077138206
  },
  {
    "id": "h-williams-0",
    "officerId": "h-williams",
    "market": "Houston",
    "customer": "Harbor Partners",
    "product": "CommLoan",
    "stage": "Lead",
    "amount": 15724903.485172417,
    "probability": 0.05825879462063313,
    "daysInStage": 77,
    "ageDays": 104,
    "expectedClose": "2026-12-22",
    "revAnnual": 534646.7184958622
  },
  {
    "id": "h-williams-1",
    "officerId": "h-williams",
    "market": "Houston",
    "customer": "Ironwood Capital",
    "product": "Deposits",
    "stage": "Lead",
    "amount": 933487.8680205336,
    "probability": 0.10893527057487518,
    "daysInStage": 64,
    "ageDays": 85,
    "expectedClose": "2026-12-19",
    "revAnnual": 4667.439340102668
  },
  {
    "id": "h-williams-2",
    "officerId": "h-williams",
    "market": "Houston",
    "customer": "Juniper Foods",
    "product": "CommLoan",
    "stage": "Proposal",
    "amount": 779233.0752810328,
    "probability": 0.4508019340923056,
    "daysInStage": 103,
    "ageDays": 188,
    "expectedClose": "2026-09-11",
    "revAnnual": 26493.92455955512
  },
  {
    "id": "h-williams-3",
    "officerId": "h-williams",
    "market": "Houston",
    "customer": "Keystone Steel",
    "product": "CommLoan",
    "stage": "Qualified",
    "amount": 2585647.287890017,
    "probability": 0.23631913154385983,
    "daysInStage": 89,
    "ageDays": 148,
    "expectedClose": "2026-10-19",
    "revAnnual": 87912.00778826058
  },
  {
    "id": "h-williams-4",
    "officerId": "h-williams",
    "market": "Houston",
    "customer": "Lakeside Medical",
    "product": "CommLoan",
    "stage": "Qualified",
    "amount": 5200728.876668954,
    "probability": 0.2736878189258277,
    "daysInStage": 32,
    "ageDays": 81,
    "expectedClose": "2026-10-15",
    "revAnnual": 176824.78180674446
  },
  {
    "id": "h-williams-5",
    "officerId": "h-williams",
    "market": "Houston",
    "customer": "Mason & Co.",
    "product": "Other",
    "stage": "Lead",
    "amount": 22812.172046862543,
    "probability": 0.07636860217899084,
    "daysInStage": 170,
    "ageDays": 178,
    "expectedClose": "2026-12-27",
    "revAnnual": 22812.172046862543
  },
  {
    "id": "h-williams-6",
    "officerId": "h-williams",
    "market": "Houston",
    "customer": "Northstar Tech",
    "product": "CommLoan",
    "stage": "Lead",
    "amount": 7356362.0759712,
    "probability": 0.08739010654389859,
    "daysInStage": 15,
    "ageDays": 44,
    "expectedClose": "2026-12-21",
    "revAnnual": 250116.31058302082
  },
  {
    "id": "d-chen-0",
    "officerId": "d-chen",
    "market": "Dallas",
    "customer": "Redwood Construction",
    "product": "CommLoan",
    "stage": "Commit",
    "amount": 17680675.92568075,
    "probability": 0.7914347203681246,
    "daysInStage": 61,
    "ageDays": 164,
    "expectedClose": "2026-08-27",
    "revAnnual": 601142.9814731455
  },
  {
    "id": "d-chen-1",
    "officerId": "d-chen",
    "market": "Dallas",
    "customer": "Summit Hospitality",
    "product": "CommLoan",
    "stage": "Proposal",
    "amount": 2595942.769954097,
    "probability": 0.4502601069863886,
    "daysInStage": 61,
    "ageDays": 149,
    "expectedClose": "2026-10-12",
    "revAnnual": 88262.0541784393
  },
  {
    "id": "d-chen-2",
    "officerId": "d-chen",
    "market": "Dallas",
    "customer": "Trinity Pharma",
    "product": "CommLoan",
    "stage": "Lead",
    "amount": 10550099.404318886,
    "probability": 0.05078554216306657,
    "daysInStage": 66,
    "ageDays": 69,
    "expectedClose": "2026-11-26",
    "revAnnual": 358703.37974684214
  },
  {
    "id": "d-chen-3",
    "officerId": "d-chen",
    "market": "Dallas",
    "customer": "Union Distributors",
    "product": "Deposits",
    "stage": "Qualified",
    "amount": 1055220.2758767398,
    "probability": 0.22753492614720017,
    "daysInStage": 21,
    "ageDays": 60,
    "expectedClose": "2026-11-11",
    "revAnnual": 5276.101379383699
  },
  {
    "id": "d-chen-4",
    "officerId": "d-chen",
    "market": "Dallas",
    "customer": "Vanguard Plastics",
    "product": "Deposits",
    "stage": "Qualified",
    "amount": 4639920.427160827,
    "probability": 0.21464541237801313,
    "daysInStage": 77,
    "ageDays": 111,
    "expectedClose": "2026-11-04",
    "revAnnual": 23199.602135804136
  },
  {
    "id": "d-chen-5",
    "officerId": "d-chen",
    "market": "Dallas",
    "customer": "Westfield Retail",
    "product": "CommLoan",
    "stage": "Lead",
    "amount": 1585817.668329033,
    "probability": 0.11780246228445322,
    "daysInStage": 36,
    "ageDays": 54,
    "expectedClose": "2026-11-05",
    "revAnnual": 53917.80072318713
  },
  {
    "id": "d-chen-6",
    "officerId": "d-chen",
    "market": "Dallas",
    "customer": "Xander Aviation",
    "product": "CommLoan",
    "stage": "Lead",
    "amount": 2728841.3219481288,
    "probability": 0.10168513727840037,
    "daysInStage": 21,
    "ageDays": 39,
    "expectedClose": "2026-12-07",
    "revAnnual": 92780.60494623639
  },
  {
    "id": "d-chen-7",
    "officerId": "d-chen",
    "market": "Dallas",
    "customer": "Yellowstone Ranch",
    "product": "Other",
    "stage": "Proposal",
    "amount": 24484.21892989427,
    "probability": 0.4725475380429998,
    "daysInStage": 88,
    "ageDays": 166,
    "expectedClose": "2026-09-05",
    "revAnnual": 24484.21892989427
  },
  {
    "id": "d-chen-8",
    "officerId": "d-chen",
    "market": "Dallas",
    "customer": "Zenith Software",
    "product": "Deposits",
    "stage": "Lead",
    "amount": 3267346.241428919,
    "probability": 0.11698600032832474,
    "daysInStage": 41,
    "ageDays": 52,
    "expectedClose": "2026-11-07",
    "revAnnual": 16336.731207144596
  },
  {
    "id": "d-garcia-0",
    "officerId": "d-garcia",
    "market": "Dallas",
    "customer": "Union Distributors",
    "product": "Other",
    "stage": "Qualified",
    "amount": 49498.91536682844,
    "probability": 0.21268982915207743,
    "daysInStage": 122,
    "ageDays": 153,
    "expectedClose": "2026-11-11",
    "revAnnual": 49498.91536682844
  },
  {
    "id": "d-garcia-1",
    "officerId": "d-garcia",
    "market": "Dallas",
    "customer": "Vanguard Plastics",
    "product": "TM",
    "stage": "Lead",
    "amount": 117786.33056208491,
    "probability": 0.13377330291550607,
    "daysInStage": 60,
    "ageDays": 62,
    "expectedClose": "2026-12-20",
    "revAnnual": 117786.33056208491
  },
  {
    "id": "d-garcia-2",
    "officerId": "d-garcia",
    "market": "Dallas",
    "customer": "Westfield Retail",
    "product": "CommLoan",
    "stage": "Closed",
    "amount": 3693911.7299618884,
    "probability": 1,
    "daysInStage": 105,
    "ageDays": 231,
    "expectedClose": "2026-07-10",
    "revAnnual": 125592.99881870422
  },
  {
    "id": "d-garcia-3",
    "officerId": "d-garcia",
    "market": "Dallas",
    "customer": "Xander Aviation",
    "product": "Other",
    "stage": "Lead",
    "amount": 40457.6849527657,
    "probability": 0.10361877784598619,
    "daysInStage": 68,
    "ageDays": 85,
    "expectedClose": "2026-12-27",
    "revAnnual": 40457.6849527657
  },
  {
    "id": "d-garcia-4",
    "officerId": "d-garcia",
    "market": "Dallas",
    "customer": "Yellowstone Ranch",
    "product": "CommLoan",
    "stage": "Qualified",
    "amount": 2322589.7408255795,
    "probability": 0.21135843328665943,
    "daysInStage": 125,
    "ageDays": 162,
    "expectedClose": "2026-11-17",
    "revAnnual": 78968.05118806972
  },
  {
    "id": "d-garcia-5",
    "officerId": "d-garcia",
    "market": "Dallas",
    "customer": "Zenith Software",
    "product": "Deposits",
    "stage": "Proposal",
    "amount": 5664478.31131048,
    "probability": 0.5112307148054243,
    "daysInStage": 52,
    "ageDays": 130,
    "expectedClose": "2026-10-04",
    "revAnnual": 28322.391556552404
  },
  {
    "id": "d-garcia-6",
    "officerId": "d-garcia",
    "market": "Dallas",
    "customer": "Alamo Equipment",
    "product": "TM",
    "stage": "Commit",
    "amount": 250208.92756758258,
    "probability": 0.8487580192741007,
    "daysInStage": 72,
    "ageDays": 173,
    "expectedClose": "2026-09-04",
    "revAnnual": 250208.92756758258
  },
  {
    "id": "d-foster-0",
    "officerId": "d-foster",
    "market": "Dallas",
    "customer": "Evergreen Realty",
    "product": "Deposits",
    "stage": "Qualified",
    "amount": 4276478.29315799,
    "probability": 0.20075344634242356,
    "daysInStage": 74,
    "ageDays": 116,
    "expectedClose": "2026-11-13",
    "revAnnual": 21382.39146578995
  },
  {
    "id": "d-foster-1",
    "officerId": "d-foster",
    "market": "Dallas",
    "customer": "Fairfield Energy",
    "product": "Other",
    "stage": "Commit",
    "amount": 71443.87836195529,
    "probability": 0.8062200189800933,
    "daysInStage": 47,
    "ageDays": 166,
    "expectedClose": "2026-09-20",
    "revAnnual": 71443.87836195529
  },
  {
    "id": "d-foster-2",
    "officerId": "d-foster",
    "market": "Dallas",
    "customer": "Galleon Logistics",
    "product": "CommLoan",
    "stage": "Proposal",
    "amount": 3318345.965485991,
    "probability": 0.5425157238496467,
    "daysInStage": 45,
    "ageDays": 120,
    "expectedClose": "2026-10-07",
    "revAnnual": 112823.7628265237
  },
  {
    "id": "d-foster-3",
    "officerId": "d-foster",
    "market": "Dallas",
    "customer": "Harbor Partners",
    "product": "Deposits",
    "stage": "Lead",
    "amount": 942755.345560251,
    "probability": 0.05744011739734561,
    "daysInStage": 85,
    "ageDays": 114,
    "expectedClose": "2026-11-11",
    "revAnnual": 4713.776727801255
  },
  {
    "id": "d-foster-4",
    "officerId": "d-foster",
    "market": "Dallas",
    "customer": "Ironwood Capital",
    "product": "Deposits",
    "stage": "Qualified",
    "amount": 907319.7614169855,
    "probability": 0.26688549560494723,
    "daysInStage": 34,
    "ageDays": 89,
    "expectedClose": "2026-10-19",
    "revAnnual": 4536.598807084928
  },
  {
    "id": "d-foster-5",
    "officerId": "d-foster",
    "market": "Dallas",
    "customer": "Juniper Foods",
    "product": "CommLoan",
    "stage": "Qualified",
    "amount": 14970368.88859432,
    "probability": 0.2906545835547149,
    "daysInStage": 35,
    "ageDays": 91,
    "expectedClose": "2026-10-17",
    "revAnnual": 508992.5422122069
  },
  {
    "id": "d-foster-6",
    "officerId": "d-foster",
    "market": "Dallas",
    "customer": "Keystone Steel",
    "product": "Deposits",
    "stage": "Proposal",
    "amount": 7146028.967720101,
    "probability": 0.4834363743895665,
    "daysInStage": 68,
    "ageDays": 144,
    "expectedClose": "2026-10-09",
    "revAnnual": 35730.14483860051
  },
  {
    "id": "d-foster-7",
    "officerId": "d-foster",
    "market": "Dallas",
    "customer": "Lakeside Medical",
    "product": "TM",
    "stage": "Closed",
    "amount": 36610.27967231348,
    "probability": 0.9827098816866056,
    "daysInStage": 14,
    "ageDays": 138,
    "expectedClose": "2026-08-06",
    "revAnnual": 36610.27967231348
  },
  {
    "id": "d-foster-8",
    "officerId": "d-foster",
    "market": "Dallas",
    "customer": "Mason & Co.",
    "product": "CommLoan",
    "stage": "Proposal",
    "amount": 3839311.4582098476,
    "probability": 0.4668406221084297,
    "daysInStage": 22,
    "ageDays": 103,
    "expectedClose": "2026-09-14",
    "revAnnual": 130536.58957913483
  },
  {
    "id": "d-foster-9",
    "officerId": "d-foster",
    "market": "Dallas",
    "customer": "Northstar Tech",
    "product": "CommLoan",
    "stage": "Proposal",
    "amount": 18165595.856785018,
    "probability": 0.5008736290503293,
    "daysInStage": 40,
    "ageDays": 112,
    "expectedClose": "2026-10-06",
    "revAnnual": 617630.2591306907
  },
  {
    "id": "d-foster-10",
    "officerId": "d-foster",
    "market": "Dallas",
    "customer": "Xander Aviation",
    "product": "TM",
    "stage": "Lead",
    "amount": 101352.16531110927,
    "probability": 0.07092865982558579,
    "daysInStage": 50,
    "ageDays": 52,
    "expectedClose": "2026-11-28",
    "revAnnual": 101352.16531110927
  },
  {
    "id": "d-foster-11",
    "officerId": "d-foster",
    "market": "Dallas",
    "customer": "Yellowstone Ranch",
    "product": "Other",
    "stage": "Lead",
    "amount": 4379.972573369741,
    "probability": 0.08016256107948722,
    "daysInStage": 83,
    "ageDays": 106,
    "expectedClose": "2026-11-28",
    "revAnnual": 4379.972573369741
  },
  {
    "id": "d-foster-12",
    "officerId": "d-foster",
    "market": "Dallas",
    "customer": "Zenith Software",
    "product": "CommLoan",
    "stage": "Commit",
    "amount": 9360282.94838176,
    "probability": 0.7510369416559115,
    "daysInStage": 43,
    "ageDays": 139,
    "expectedClose": "2026-08-13",
    "revAnnual": 318249.62024497986
  },
  {
    "id": "d-foster-13",
    "officerId": "d-foster",
    "market": "Dallas",
    "customer": "Alamo Equipment",
    "product": "Deposits",
    "stage": "Closed",
    "amount": 1565237.5440216535,
    "probability": 0.9879039052175358,
    "daysInStage": 55,
    "ageDays": 195,
    "expectedClose": "2026-07-21",
    "revAnnual": 7826.187720108268
  }
]